pylint_topology/__init__.py
pylint_topology-0.1.2.dist-info/METADATA
pylint_topology-0.1.2.dist-info/RECORD
pylint_topology-0.1.2.dist-info/WHEEL
pylint_topology-0.1.2.dist-info/top_level.txt
