Metadata-Version: 2.1
Name: pylint-topology
Version: 0.1.2
Summary: check module topology in pylint
Home-page: https://github.com/LKI/pylint_topology
Author: Lirian Su
Author-email: liriansu@gmail.com
License: GPLv2
Platform: UNKNOWN
Classifier: Programming Language :: Python :: 2
Classifier: Programming Language :: Python :: 2.7
Classifier: Programming Language :: Python :: 3
Classifier: Programming Language :: Python :: 3.5
Classifier: Programming Language :: Python :: 3.6
Classifier: Programming Language :: Python :: 3.7
Requires-Dist: pylint (>=2.0)
